meta_ads_mcp/__init__.py
meta_ads_mcp/__main__.py
meta_ads_mcp/core/__init__.py
meta_ads_mcp/core/accounts.py
meta_ads_mcp/core/ads.py
meta_ads_mcp/core/ads_library.py
meta_ads_mcp/core/adsets.py
meta_ads_mcp/core/api.py
meta_ads_mcp/core/auth.py
meta_ads_mcp/core/authentication.py
meta_ads_mcp/core/budget_schedules.py
meta_ads_mcp/core/callback_server.py
meta_ads_mcp/core/campaigns.py
meta_ads_mcp/core/duplication.py
meta_ads_mcp/core/http_auth_integration.py
meta_ads_mcp/core/insights.py
meta_ads_mcp/core/pipeboard_auth.py
meta_ads_mcp/core/reports.py
meta_ads_mcp/core/resources.py
meta_ads_mcp/core/server.py
meta_ads_mcp/core/utils.py
rgo_meta_ads_mcp-0.1.2.dist-info/METADATA
rgo_meta_ads_mcp-0.1.2.dist-info/WHEEL
rgo_meta_ads_mcp-0.1.2.dist-info/entry_points.txt
rgo_meta_ads_mcp-0.1.2.dist-info/licenses/LICENSE
rgo_meta_ads_mcp-0.1.2.dist-info/RECORD
